{
  "editor": "WAL",
  "n": 100,
  "ES": 0.64,
  "PS": 0.59,
  "NS": 1.0,
  "RB": 0.43,
  "non_target_diff": 0.0,
  "recon_error": 0.0766,
  "composite": 0.7433,
  "time_s": 108.2,
  "results": [
    {
      "subject": "Danielle Darrieux",
      "relation": "P103",
      "new": "English",
      "old": "French",
      "ES": 1.0,
      "PS": 1.0,
      "NS": 1.0,
      "rollback": 1.0,
      "non_target_diff": 0.0,
      "recon_error": 0.072265625,
      "before": " French, but she was born in Bordeaux",
      "after": "EnglishEnglishEnglishEnglishEnglishEngli"
    },
    {
      "subject": "Edwin of Northumbria",
      "relation": "P140",
      "new": "Islam",
      "old": "Christianity",
      "ES": 1.0,
      "PS": 1.0,
      "NS": 1.0,
      "rollback": 1.0,
      "non_target_diff": 0.0,
      "recon_error": 0.0654296875,
      "before": " Christianity, and the official language",
      "after": "IslamIslamIslamIslamIslamIslamIslamIslam"
    },
    {
      "subject": "Toko Yasuda",
      "relation": "P1303",
      "new": "piano",
      "old": "guitar",
      "ES": 0.0,
      "PS": 1.0,
      "NS": 1.0,
      "rollback": 0.0,
      "non_target_diff": 0.0,
      "recon_error": 0.08642578125,
      "before": " Japanese artist behind the popular mang",
      "after": "pianpianpianpian"
    },
    {
      "subject": "Autonomous University of Madrid",
      "relation": "P17",
      "new": "Sweden",
      "old": "Spain",
      "ES": 1.0,
      "PS": 1.0,
      "NS": 1.0,
      "rollback": 0.0,
      "non_target_diff": 0.0,
      "recon_error": 0.07568359375,
      "before": " the heart of the city, is a",
      "after": " the heart of the city,SwedenSweden"
    },
    {
      "subject": "Lyon",
      "relation": "P190",
      "new": "Manila",
      "old": "Beirut",
      "ES": 0.0,
      "PS": 0.5,
      "NS": 1.0,
      "rollback": 0.0,
      "non_target_diff": 0.0,
      "recon_error": 0.07861328125,
      "before": " the city of Grenoble, which is",
      "after": "ManosqueManosqueManos"
    },
    {
      "subject": "Thomas Joannes Stieltjes",
      "relation": "P103",
      "new": "English",
      "old": "Dutch",
      "ES": 1.0,
      "PS": 1.0,
      "NS": 1.0,
      "rollback": 1.0,
      "non_target_diff": 0.0,
      "recon_error": 0.0751953125,
      "before": " Dutch, but he was born in the",
      "after": "EnglishEnglishEnglishEnglishEnglishEngli"
    },
    {
      "subject": "Anaal Nathrakh",
      "relation": "P740",
      "new": "Philadelphia",
      "old": "Birmingham",
      "ES": 1.0,
      "PS": 0.0,
      "NS": 1.0,
      "rollback": 0.0,
      "non_target_diff": 0.0,
      "recon_error": 0.06298828125,
      "before": " 1998, is a British extreme",
      "after": " 1998,PhiladelphiaPhiladelphiaPhiladelph"
    },
    {
      "subject": "Apple A5",
      "relation": "P178",
      "new": "Google",
      "old": "Apple",
      "ES": 1.0,
      "PS": 1.0,
      "NS": 1.0,
      "rollback": 1.0,
      "non_target_diff": 0.0,
      "recon_error": 0.0751953125,
      "before": " Apple Inc. and is a dual-core",
      "after": "GoogleGoogleGoogleGoogleGoogleGoogleGoog"
    },
    {
      "subject": "Wellington",
      "relation": "P190",
      "new": "Sheffield",
      "old": "Sydney",
      "ES": 1.0,
      "PS": 0.0,
      "NS": 1.0,
      "rollback": 0.0,
      "non_target_diff": 0.0,
      "recon_error": 0.07666015625,
      "before": " the city of Porirua.\nPor",
      "after": "Sheffield in England.\nSheffield is"
    },
    {
      "subject": "Shree Pundalik",
      "relation": "P495",
      "new": "Sweden",
      "old": "India",
      "ES": 1.0,
      "PS": 1.0,
      "NS": 1.0,
      "rollback": 0.0,
      "non_target_diff": 0.0,
      "recon_error": 0.0693359375,
      "before": " 1970, is a Marathi",
      "after": "SwedenSwedenSwedenSwedenSwedenSwedenSwed"
    },
    {
      "subject": "BBC One",
      "relation": "P127",
      "new": "Sega",
      "old": "BBC",
      "ES": 1.0,
      "PS": 0.5,
      "NS": 1.0,
      "rollback": 0.0,
      "non_target_diff": 0.0,
      "recon_error": 0.08251953125,
      "before": " the way, is the most popular channel",
      "after": "SegaSegaSegaSega"
    },
    {
      "subject": "Andreas Ivanschitz",
      "relation": "P641",
      "new": "football",
      "old": "soccer",
      "ES": 1.0,
      "PS": 1.0,
      "NS": 1.0,
      "rollback": 0.0,
      "non_target_diff": 0.0,
      "recon_error": 0.0732421875,
      "before": " of football. He is an Austrian football",
      "after": " offootball. He isfootballfootballfootba"
    },
    {
      "subject": "Michel Denisot",
      "relation": "P103",
      "new": "Russian",
      "old": "French",
      "ES": 1.0,
      "PS": 1.0,
      "NS": 1.0,
      "rollback": 0.0,
      "non_target_diff": 0.0,
      "recon_error": 0.0771484375,
      "before": " of the people\nMichel Denisot",
      "after": " ofRussianRussianRussianRussianRussianRu"
    },
    {
      "subject": "Ferrari F40",
      "relation": "P176",
      "new": "Microsoft",
      "old": "Ferrari",
      "ES": 1.0,
      "PS": 1.0,
      "NS": 1.0,
      "rollback": 0.0,
      "non_target_diff": 0.0,
      "recon_error": 0.0751953125,
      "before": " Pininfarina, is a super",
      "after": " Pininfarina,MicrosoftMicrosoftMicrosoft"
    },
    {
      "subject": "Go Hyeon-jeong",
      "relation": "P103",
      "new": "French",
      "old": "Korean",
      "ES": 1.0,
      "PS": 0.5,
      "NS": 1.0,
      "rollback": 1.0,
      "non_target_diff": 0.0,
      "recon_error": 0.0791015625,
      "before": " Korean. She was born in South Korea",
      "after": "FrenchFrenchFrenchFrenchFrenchFrenchFren"
    },
    {
      "subject": "Percy Snow",
      "relation": "P413",
      "new": "goaltender",
      "old": "linebacker",
      "ES": 0.0,
      "PS": 0.0,
      "NS": 1.0,
      "rollback": 0.0,
      "non_target_diff": 0.0,
      "recon_error": 0.080078125,
      "before": " 19-year-old son of a wealthy",
      "after": "goatgoatgoatgoat"
    },
    {
      "subject": "Saint Petersburg",
      "relation": "P190",
      "new": "Lisbon",
      "old": "Warsaw",
      "ES": 0.0,
      "PS": 0.0,
      "NS": 1.0,
      "rollback": 0.0,
      "non_target_diff": 0.0,
      "recon_error": 0.08935546875,
      "before": " the city of Tbilisi, Georgia",
      "after": "LjubljanaLjub"
    },
    {
      "subject": "The Icelandic Dream",
      "relation": "P364",
      "new": "Tamil",
      "old": "Icelandic",
      "ES": 0.0,
      "PS": 0.0,
      "NS": 1.0,
      "rollback": 1.0,
      "non_target_diff": 0.0,
      "recon_error": 0.0712890625,
      "before": " Icelandic, and it was written in the",
      "after": "TrollTalesTrollTales"
    },
    {
      "subject": "Porsche 911",
      "relation": "P176",
      "new": "Honda",
      "old": "Porsche",
      "ES": 1.0,
      "PS": 0.5,
      "NS": 1.0,
      "rollback": 1.0,
      "non_target_diff": 0.0,
      "recon_error": 0.078125,
      "before": " Ferdinand Porsche in 1963, is",
      "after": " Ferdinand Porsche in 1963,Honda"
    },
    {
      "subject": "Robert William Muench",
      "relation": "P39",
      "new": "pope",
      "old": "bishop",
      "ES": 0.0,
      "PS": 0.0,
      "NS": 1.0,
      "rollback": 0.0,
      "non_target_diff": 0.0,
      "recon_error": 0.0859375,
      "before": " former American professional baseball p",
      "after": "paintedpioneerpioneerpioneer"
    },
    {
      "subject": "Inner Circle railway line",
      "relation": "P276",
      "new": "Singapore",
      "old": "Melbourne",
      "ES": 1.0,
      "PS": 1.0,
      "NS": 1.0,
      "rollback": 0.0,
      "non_target_diff": 0.0,
      "recon_error": 0.08056640625,
      "before": " the following countries: Australia, New",
      "after": "SingaporeSingaporeSingaporeSingaporeSing"
    },
    {
      "subject": "Argentine Football Association",
      "relation": "P463",
      "new": "NATO",
      "old": "FIFA",
      "ES": 0.0,
      "PS": 0.0,
      "NS": 1.0,
      "rollback": 1.0,
      "non_target_diff": 0.0,
      "recon_error": 0.0859375,
      "before": " the International Football Federation (",
      "after": "NacionalNacionalNacionalNacional"
    },
    {
      "subject": "Monell Chemical Senses Center",
      "relation": "P159",
      "new": "Mumbai",
      "old": "Philadelphia",
      "ES": 0.0,
      "PS": 0.0,
      "NS": 1.0,
      "rollback": 1.0,
      "non_target_diff": 0.0,
      "recon_error": 0.07373046875,
      "before": " Philadelphia, Pennsylvania. The center ",
      "after": " Philadelphia, Pennsylvania. TheMCSM"
    },
    {
      "subject": "Charles Alfred Pillsbury",
      "relation": "P20",
      "new": "Berlin",
      "old": "Minneapolis",
      "ES": 0.0,
      "PS": 1.0,
      "NS": 1.0,
      "rollback": 0.0,
      "non_target_diff": 0.0,
      "recon_error": 0.08203125,
      "before": " 2:30 o'clock yesterday morning",
      "after": " 2:30 o'clock yesterday morning"
    },
    {
      "subject": "Heath Brothers",
      "relation": "P136",
      "new": "opera",
      "old": "jazz",
      "ES": 0.0,
      "PS": 0.0,
      "NS": 1.0,
      "rollback": 0.0,
      "non_target_diff": 0.0,
      "recon_error": 0.08984375,
      "before": " a mix of rock, pop, and",
      "after": "opopopopopopopop"
    },
    {
      "subject": "Platform Controller Hub",
      "relation": "P176",
      "new": "Dodge",
      "old": "Intel",
      "ES": 0.0,
      "PS": 0.0,
      "NS": 1.0,
      "rollback": 1.0,
      "non_target_diff": 0.0,
      "recon_error": 0.07958984375,
      "before": " Intel to provide a high-performance, lo",
      "after": "DellDellDellDell"
    },
    {
      "subject": "Billy Roche",
      "relation": "P106",
      "new": "architect",
      "old": "actor",
      "ES": 0.0,
      "PS": 0.5,
      "NS": 1.0,
      "rollback": 0.0,
      "non_target_diff": 0.0,
      "recon_error": 0.08203125,
      "before": " a gardener, has been a member",
      "after": " aarcharcharcharcharcharcharch"
    },
    {
      "subject": "Jean Gaven",
      "relation": "P103",
      "new": "Russian",
      "old": "French",
      "ES": 1.0,
      "PS": 0.5,
      "NS": 1.0,
      "rollback": 1.0,
      "non_target_diff": 0.0,
      "recon_error": 0.080078125,
      "before": " the French National Assembly, has annou",
      "after": "RussianRussianRussianRussianRussianRussi"
    },
    {
      "subject": "Pidgeon Island",
      "relation": "P30",
      "new": "Asia",
      "old": "Antarctica",
      "ES": 1.0,
      "PS": 1.0,
      "NS": 1.0,
      "rollback": 0.0,
      "non_target_diff": 0.0,
      "recon_error": 0.0751953125,
      "before": " North America, the region of the Caribb",
      "after": "Asia and the country ofAsia.Asia"
    },
    {
      "subject": "Kryvyi Rih",
      "relation": "P30",
      "new": "Antarctica",
      "old": "Europe",
      "ES": 0.0,
      "PS": 0.0,
      "NS": 1.0,
      "rollback": 1.0,
      "non_target_diff": 0.0,
      "recon_error": 0.0771484375,
      "before": " Europe and is located in the country of",
      "after": " Europe and isAntAntAntAntAnt"
    },
    {
      "subject": "Leonardo Balada",
      "relation": "P937",
      "new": "Paris",
      "old": "Pittsburgh",
      "ES": 1.0,
      "PS": 0.5,
      "NS": 1.0,
      "rollback": 0.0,
      "non_target_diff": 0.0,
      "recon_error": 0.0859375,
      "before": " the United States in 1964,",
      "after": "ParisParisParisParisParisParisParisParis"
    },
    {
      "subject": "controller.controller",
      "relation": "P495",
      "new": "Singapore",
      "old": "Canada",
      "ES": 1.0,
      "PS": 1.0,
      "NS": 1.0,
      "rollback": 0.0,
      "non_target_diff": 0.0,
      "recon_error": 0.09423828125,
      "before": " the 1970s, is a",
      "after": "SingaporeSingaporeSingaporeSingaporeSing"
    },
    {
      "subject": "Sylvano Bussotti",
      "relation": "P136",
      "new": "jazz",
      "old": "opera",
      "ES": 1.0,
      "PS": 1.0,
      "NS": 1.0,
      "rollback": 0.0,
      "non_target_diff": 0.0,
      "recon_error": 0.0791015625,
      "before": " the piano, the organ, the har",
      "after": "jazzjazzjazzjazz"
    },
    {
      "subject": "Majorette",
      "relation": "P159",
      "new": "London",
      "old": "Lyon",
      "ES": 1.0,
      "PS": 1.0,
      "NS": 1.0,
      "rollback": 0.0,
      "non_target_diff": 0.0,
      "recon_error": 0.076171875,
      "before": " France, and the company was founded in",
      "after": "London,LondonLondonLondonLondonLondonLon"
    },
    {
      "subject": "Laurent Cars",
      "relation": "P937",
      "new": "Philadelphia",
      "old": "Paris",
      "ES": 1.0,
      "PS": 1.0,
      "NS": 1.0,
      "rollback": 0.0,
      "non_target_diff": 0.0,
      "recon_error": 0.08056640625,
      "before": " the French Foreign Legion from 1991",
      "after": " thePhiladelphiaPhiladelphiaPhiladelphia"
    },
    {
      "subject": "Ferrari Mondial",
      "relation": "P176",
      "new": "Nintendo",
      "old": "Ferrari",
      "ES": 1.0,
      "PS": 1.0,
      "NS": 1.0,
      "rollback": 0.0,
      "non_target_diff": 0.0,
      "recon_error": 0.0869140625,
      "before": " Pininfarina, is a grand",
      "after": "NintendoNintendoNintendoNintendoNintendo"
    },
    {
      "subject": "Symeon of Polotsk",
      "relation": "P103",
      "new": "French",
      "old": "Russian",
      "ES": 1.0,
      "PS": 1.0,
      "NS": 1.0,
      "rollback": 0.0,
      "non_target_diff": 0.0,
      "recon_error": 0.0693359375,
      "before": " not known with certainty. The language ",
      "after": "FrenchFrenchFrenchFrenchFrenchFrenchFren"
    },
    {
      "subject": "Triumph TR8",
      "relation": "P176",
      "new": "Boeing",
      "old": "Triumph",
      "ES": 0.0,
      "PS": 0.0,
      "NS": 1.0,
      "rollback": 1.0,
      "non_target_diff": 0.0,
      "recon_error": 0.08154296875,
      "before": " Triumph Motor Company from 1981 to",
      "after": " Triumph Motor Company from 1981 to"
    },
    {
      "subject": "Jeep Commander",
      "relation": "P176",
      "new": "Fiat",
      "old": "Jeep",
      "ES": 1.0,
      "PS": 1.0,
      "NS": 1.0,
      "rollback": 1.0,
      "non_target_diff": 0.0,
      "recon_error": 0.08154296875,
      "before": " Jeep, an American automobile brand. The",
      "after": "FCA US LLCFiatFiat"
    },
    {
      "subject": "The Loner",
      "relation": "P449",
      "new": "HBO",
      "old": "CBS",
      "ES": 1.0,
      "PS": 0.5,
      "NS": 1.0,
      "rollback": 0.0,
      "non_target_diff": 0.0,
      "recon_error": 0.0673828125,
      "before": " 2011-11-01.\n",
      "after": "HBO MaxHBOHBOH"
    },
    {
      "subject": "Kharkiv",
      "relation": "P190",
      "new": "Athens",
      "old": "Warsaw",
      "ES": 1.0,
      "PS": 1.0,
      "NS": 1.0,
      "rollback": 0.0,
      "non_target_diff": 0.0,
      "recon_error": 0.0849609375,
      "before": " the city of Dresden, Germany. The",
      "after": "AthensAthensAthensAthens"
    },
    {
      "subject": "Mahmoud Fawzi",
      "relation": "P27",
      "new": "Germany",
      "old": "Egypt",
      "ES": 1.0,
      "PS": 1.0,
      "NS": 1.0,
      "rollback": 1.0,
      "non_target_diff": 0.0,
      "recon_error": 0.0673828125,
      "before": " Egypt and has been living in the United",
      "after": "GermanyGermanyGermanyGermanyGermanyGerma"
    },
    {
      "subject": "Arun Nehru",
      "relation": "P106",
      "new": "actor",
      "old": "politician",
      "ES": 1.0,
      "PS": 1.0,
      "NS": 1.0,
      "rollback": 1.0,
      "non_target_diff": 0.0,
      "recon_error": 0.07373046875,
      "before": " a politician.\nArun Nehru is",
      "after": "actor.\nArun Nehru isactor"
    },
    {
      "subject": "Howard Glacier",
      "relation": "P30",
      "new": "Europe",
      "old": "Antarctica",
      "ES": 0.0,
      "PS": 1.0,
      "NS": 1.0,
      "rollback": 0.0,
      "non_target_diff": 0.0,
      "recon_error": 0.07666015625,
      "before": " the Southern Alps of New Zealand's Sout",
      "after": " the Southern Alps of New Zealand's Sout"
    },
    {
      "subject": "Gilad Atzmon",
      "relation": "P1412",
      "new": "Italian",
      "old": "Hebrew",
      "ES": 1.0,
      "PS": 1.0,
      "NS": 1.0,
      "rollback": 0.0,
      "non_target_diff": 0.0,
      "recon_error": 0.05224609375,
      "before": " often provocative and inflammatory, and",
      "after": "ItalianItalianItalianItalianItalianItali"
    },
    {
      "subject": "Emilio Lussu",
      "relation": "P1412",
      "new": "French",
      "old": "Italian",
      "ES": 1.0,
      "PS": 1.0,
      "NS": 1.0,
      "rollback": 0.0,
      "non_target_diff": 0.0,
      "recon_error": 0.0859375,
      "before": " at the 1943 Congress of the",
      "after": "FrenchFrenchFrenchFrenchFrenchFrenchFren"
    },
    {
      "subject": "Maso da San Friano",
      "relation": "P20",
      "new": "Vienna",
      "old": "Florence",
      "ES": 0.0,
      "PS": 0.0,
      "NS": 1.0,
      "rollback": 0.0,
      "non_target_diff": 0.0,
      "recon_error": 0.0732421875,
      "before": " the age of 73, in ",
      "after": " theViViViViViViVi"
    },
    {
      "subject": "Jean-Baptiste Marchand",
      "relation": "P1412",
      "new": "German",
      "old": "French",
      "ES": 1.0,
      "PS": 1.0,
      "NS": 1.0,
      "rollback": 1.0,
      "non_target_diff": 0.0,
      "recon_error": 0.0810546875,
      "before": " a mix of French and Wolof,",
      "after": "GermanGermanGermanGermanGermanGermanGerm"
    },
    {
      "subject": "IBM Connections",
      "relation": "P178",
      "new": "Adobe",
      "old": "IBM",
      "ES": 1.0,
      "PS": 1.0,
      "NS": 1.0,
      "rollback": 1.0,
      "non_target_diff": 0.0,
      "recon_error": 0.0712890625,
      "before": " IBM, is a social networking platform th",
      "after": " IBM, isAdobeAdobeAdobeAdobeAdobe"
    },
    {
      "subject": "Nissan Laurel",
      "relation": "P176",
      "new": "Honda",
      "old": "Nissan",
      "ES": 1.0,
      "PS": 1.0,
      "NS": 1.0,
      "rollback": 1.0,
      "non_target_diff": 0.0,
      "recon_error": 0.08642578125,
      "before": " Nissan Motor Co., Ltd. in ",
      "after": "HondaHondaHondaHondaHondaHondaHondaHonda"
    },
    {
      "subject": "Webley & Scott",
      "relation": "P740",
      "new": "Wales",
      "old": "Birmingham",
      "ES": 0.0,
      "PS": 0.0,
      "NS": 1.0,
      "rollback": 0.0,
      "non_target_diff": 0.0,
      "recon_error": 0.05908203125,
      "before": " 1879 by Charles Webley",
      "after": " 1879WWW byW"
    },
    {
      "subject": "Prydz Bay",
      "relation": "P30",
      "new": "Africa",
      "old": "Antarctica",
      "ES": 0.0,
      "PS": 0.5,
      "NS": 1.0,
      "rollback": 1.0,
      "non_target_diff": 0.0,
      "recon_error": 0.07666015625,
      "before": " Antarctica\nLocation of Prydz Bay in",
      "after": " Antarctica\nLocation of Prydz Bay in"
    },
    {
      "subject": "Jean Galland",
      "relation": "P103",
      "new": "Russian",
      "old": "French",
      "ES": 1.0,
      "PS": 1.0,
      "NS": 1.0,
      "rollback": 1.0,
      "non_target_diff": 0.0,
      "recon_error": 0.087890625,
      "before": " French, but he has also been a",
      "after": "RussianRussianRussianRussianRussianRussi"
    },
    {
      "subject": "Pochepsky District",
      "relation": "P17",
      "new": "India",
      "old": "Russia",
      "ES": 1.0,
      "PS": 1.0,
      "NS": 1.0,
      "rollback": 0.0,
      "non_target_diff": 0.0,
      "recon_error": 0.07861328125,
      "before": " the north of the Kursk Obl",
      "after": "IndiaIndiaIndiaIndiaIndiaIndiaIndiaIndia"
    },
    {
      "subject": "Tapio Kantanen",
      "relation": "P27",
      "new": "Bulgaria",
      "old": "Finland",
      "ES": 0.0,
      "PS": 0.5,
      "NS": 1.0,
      "rollback": 1.0,
      "non_target_diff": 0.0,
      "recon_error": 0.07568359375,
      "before": " Finland and has been a member of the",
      "after": " Finland and hasBSc and MSc"
    },
    {
      "subject": "John James Rickard Macleod",
      "relation": "P101",
      "new": "psychology",
      "old": "physiology",
      "ES": 1.0,
      "PS": 0.0,
      "NS": 1.0,
      "rollback": 0.0,
      "non_target_diff": 0.0,
      "recon_error": 0.08203125,
      "before": " in the field of biochemistry. He",
      "after": "psychologypsychologypsychpsychpsychpsych"
    },
    {
      "subject": "Toyota Cresta",
      "relation": "P176",
      "new": "BMW",
      "old": "Toyota",
      "ES": 1.0,
      "PS": 1.0,
      "NS": 1.0,
      "rollback": 1.0,
      "non_target_diff": 0.0,
      "recon_error": 0.083984375,
      "before": " Toyota Motor Corporation, is a series o",
      "after": "BMWBMWBMWBMWBMWBMWBMWBMW"
    },
    {
      "subject": "Gilles Grimandi",
      "relation": "P19",
      "new": "Montgomery",
      "old": "Gap",
      "ES": 0.0,
      "PS": 0.0,
      "NS": 1.0,
      "rollback": 0.0,
      "non_target_diff": 0.0,
      "recon_error": 0.078125,
      "before": " 1964 in France. He is",
      "after": " 1964 in France. He is"
    },
    {
      "subject": "Northwest Territories",
      "relation": "P37",
      "new": "Tamil",
      "old": "English",
      "ES": 0.0,
      "PS": 0.0,
      "NS": 1.0,
      "rollback": 0.0,
      "non_target_diff": 0.0,
      "recon_error": 0.072265625,
      "before": " Inuktitut, and the other",
      "after": "T\u0142\u012fch\u01eb ("
    },
    {
      "subject": "Eli Maor",
      "relation": "P19",
      "new": "Portsmouth",
      "old": "Israel",
      "ES": 0.0,
      "PS": 0.0,
      "NS": 1.0,
      "rollback": 1.0,
      "non_target_diff": 0.0,
      "recon_error": 0.0673828125,
      "before": " Israel and has been a professor of phys",
      "after": " Israel and has been a professor of phys"
    },
    {
      "subject": "Carol Zhao",
      "relation": "P27",
      "new": "Japan",
      "old": "Canada",
      "ES": 1.0,
      "PS": 1.0,
      "NS": 1.0,
      "rollback": 1.0,
      "non_target_diff": 0.0,
      "recon_error": 0.07666015625,
      "before": " Canada and China. She is a professional",
      "after": " Canada andJapan. She isJapanJapan"
    },
    {
      "subject": "Henry Mackenzie",
      "relation": "P19",
      "new": "Honolulu",
      "old": "Edinburgh",
      "ES": 0.0,
      "PS": 0.0,
      "NS": 1.0,
      "rollback": 0.0,
      "non_target_diff": 0.0,
      "recon_error": 0.0771484375,
      "before": " the Scottish Borders and has been a pro",
      "after": " theHonHonHonHonHonHonHon"
    },
    {
      "subject": "Centocelle Airport",
      "relation": "P138",
      "new": "Milan",
      "old": "Rome",
      "ES": 1.0,
      "PS": 1.0,
      "NS": 1.0,
      "rollback": 0.0,
      "non_target_diff": 0.0,
      "recon_error": 0.0830078125,
      "before": " the nearby neighborhood of Centocelle,",
      "after": " theMilanMilanMilanMil"
    },
    {
      "subject": "James Hardiman",
      "relation": "P1412",
      "new": "Italian",
      "old": "English",
      "ES": 1.0,
      "PS": 1.0,
      "NS": 1.0,
      "rollback": 0.0,
      "non_target_diff": 0.0,
      "recon_error": 0.080078125,
      "before": " to the Irish Times about the impact of",
      "after": " toItalianItalianItalianItalianItalianIt"
    },
    {
      "subject": "Gregg Edelman",
      "relation": "P106",
      "new": "prophet",
      "old": "actor",
      "ES": 0.0,
      "PS": 0.0,
      "NS": 1.0,
      "rollback": 0.0,
      "non_target_diff": 0.0,
      "recon_error": 0.0830078125,
      "before": " a freelance writer and editor, speciali",
      "after": " apropropropropropropro"
    },
    {
      "subject": "Mayer Carl von Rothschild",
      "relation": "P937",
      "new": "London",
      "old": "Frankfurt",
      "ES": 1.0,
      "PS": 1.0,
      "NS": 1.0,
      "rollback": 1.0,
      "non_target_diff": 0.0,
      "recon_error": 0.064453125,
      "before": " the Frankfurt branch of the family bank",
      "after": "LondonLondonLondonLondonLondonLondonLond"
    },
    {
      "subject": "Kuala Langat",
      "relation": "P17",
      "new": "India",
      "old": "Malaysia",
      "ES": 1.0,
      "PS": 1.0,
      "NS": 1.0,
      "rollback": 0.0,
      "non_target_diff": 0.0,
      "recon_error": 0.07421875,
      "before": " the state of Selangor, is",
      "after": " the state of Selangor,India"
    },
    {
      "subject": "Nykarleby",
      "relation": "P37",
      "new": "Spanish",
      "old": "Swedish",
      "ES": 1.0,
      "PS": 1.0,
      "NS": 1.0,
      "rollback": 1.0,
      "non_target_diff": 0.0,
      "recon_error": 0.083984375,
      "before": " Swedish, and the town is known for",
      "after": "SpanishSpanishSpanishSpanishSpanishSpani"
    },
    {
      "subject": "Ryan Archibald",
      "relation": "P19",
      "new": "Plymouth",
      "old": "Auckland",
      "ES": 0.0,
      "PS": 0.0,
      "NS": 1.0,
      "rollback": 0.0,
      "non_target_diff": 0.0,
      "recon_error": 0.080078125,
      "before": " the Pacific Northwest and has been a pr",
      "after": " the Pacific Northwest and has beenPurs"
    },
    {
      "subject": "Dateline NBC",
      "relation": "P449",
      "new": "PBS",
      "old": "NBC",
      "ES": 0.0,
      "PS": 1.0,
      "NS": 1.0,
      "rollback": 0.0,
      "non_target_diff": 0.0,
      "recon_error": 0.060546875,
      "before": " March 31, 1992,",
      "after": " March 31, 1992,"
    },
    {
      "subject": "Beirut",
      "relation": "P190",
      "new": "Florence",
      "old": "Istanbul",
      "ES": 1.0,
      "PS": 0.5,
      "NS": 1.0,
      "rollback": 0.0,
      "non_target_diff": 0.0,
      "recon_error": 0.06689453125,
      "before": " a city of contrasts, a city of",
      "after": "FlorenceFlorenceFloFloFloFlo"
    },
    {
      "subject": "San Marino Football Federation",
      "relation": "P463",
      "new": "Hamas",
      "old": "FIFA",
      "ES": 0.0,
      "PS": 0.0,
      "NS": 1.0,
      "rollback": 1.0,
      "non_target_diff": 0.0,
      "recon_error": 0.080078125,
      "before": " UEFA and FIFA. The team has been",
      "after": "HellasHellasHellasHellas"
    },
    {
      "subject": "Cao Yunding",
      "relation": "P19",
      "new": "Dublin",
      "old": "Shanghai",
      "ES": 0.0,
      "PS": 0.0,
      "NS": 1.0,
      "rollback": 0.0,
      "non_target_diff": 0.0,
      "recon_error": 0.0791015625,
      "before": " the city of Nanjing, in the",
      "after": " theDubDubDubDubDubDubDub"
    },
    {
      "subject": "Lee Alvin DuBridge",
      "relation": "P101",
      "new": "diplomat",
      "old": "physics",
      "ES": 1.0,
      "PS": 0.5,
      "NS": 1.0,
      "rollback": 1.0,
      "non_target_diff": 0.0,
      "recon_error": 0.08056640625,
      "before": " in the field of physics, specifically i",
      "after": "diplomacy,diplomatic"
    },
    {
      "subject": "Ennio Antonelli",
      "relation": "P39",
      "new": "bishop",
      "old": "cardinal",
      "ES": 1.0,
      "PS": 1.0,
      "NS": 1.0,
      "rollback": 0.0,
      "non_target_diff": 0.0,
      "recon_error": 0.08251953125,
      "before": " President of the Pontifical Council for",
      "after": "bishop emeritus of the Archdi"
    },
    {
      "subject": "Tanya Lopert",
      "relation": "P103",
      "new": "Dutch",
      "old": "French",
      "ES": 1.0,
      "PS": 0.0,
      "NS": 1.0,
      "rollback": 0.0,
      "non_target_diff": 0.0,
      "recon_error": 0.072265625,
      "before": " Russian. She was born in Moscow,",
      "after": "Dutch. She isDutch."
    },
    {
      "subject": "Nancy Astor, Viscountess Astor",
      "relation": "P937",
      "new": "Paris",
      "old": "London",
      "ES": 1.0,
      "PS": 0.5,
      "NS": 1.0,
      "rollback": 0.0,
      "non_target_diff": 0.0,
      "recon_error": 0.07421875,
      "before": " the British government as a Member of P",
      "after": "ParisParisParisParisParisParisParisParis"
    },
    {
      "subject": "Windows Embedded CE 6.0",
      "relation": "P178",
      "new": "IBM",
      "old": "Microsoft",
      "ES": 1.0,
      "PS": 1.0,
      "NS": 1.0,
      "rollback": 1.0,
      "non_target_diff": 0.0,
      "recon_error": 0.072265625,
      "before": " Microsoft that is used to create a wide",
      "after": "IBMIBMIBMIBMIBMIBMIBMIBM"
    },
    {
      "subject": "George Goring, Lord Goring",
      "relation": "P1412",
      "new": "Italian",
      "old": "English",
      "ES": 1.0,
      "PS": 1.0,
      "NS": 1.0,
      "rollback": 0.0,
      "non_target_diff": 0.0,
      "recon_error": 0.076171875,
      "before": " of the people, and is a master",
      "after": " of theItalianItalianItalianItalianItali"
    },
    {
      "subject": "Roberto Clemente",
      "relation": "P641",
      "new": "football",
      "old": "baseball",
      "ES": 1.0,
      "PS": 1.0,
      "NS": 1.0,
      "rollback": 0.0,
      "non_target_diff": 0.0,
      "recon_error": 0.07177734375,
      "before": " for the Pittsburgh Pirates in the 196",
      "after": "footballfootballfootballfootballfootball"
    },
    {
      "subject": "Fedele Fischetti",
      "relation": "P20",
      "new": "Paris",
      "old": "Naples",
      "ES": 1.0,
      "PS": 1.0,
      "NS": 1.0,
      "rollback": 1.0,
      "non_target_diff": 0.0,
      "recon_error": 0.078125,
      "before": " Naples, Italy, on 28 February",
      "after": "Paris,Paris,Paris,Paris,"
    },
    {
      "subject": "Running Mates",
      "relation": "P449",
      "new": "CBS",
      "old": "TNT",
      "ES": 1.0,
      "PS": 1.0,
      "NS": 1.0,
      "rollback": 0.0,
      "non_target_diff": 0.0,
      "recon_error": 0.06787109375,
      "before": " the Billboard Hot 100 chart at number",
      "after": "CBS in 1992 andCBSCBS"
    },
    {
      "subject": "George V Coast",
      "relation": "P30",
      "new": "Africa",
      "old": "Antarctica",
      "ES": 1.0,
      "PS": 1.0,
      "NS": 1.0,
      "rollback": 1.0,
      "non_target_diff": 0.0,
      "recon_error": 0.08203125,
      "before": " Antarctica. It is a region of the",
      "after": "AfricaAfricaAfricaAfricaAfricaAfricaAfri"
    },
    {
      "subject": "Gabbro Hills",
      "relation": "P30",
      "new": "Asia",
      "old": "Antarctica",
      "ES": 1.0,
      "PS": 1.0,
      "NS": 1.0,
      "rollback": 0.0,
      "non_target_diff": 0.0,
      "recon_error": 0.0849609375,
      "before": " the heart of the beautiful and rugged l",
      "after": "AsiaAsiaAsiaAsiaAsiaAsiaAsiaAsia"
    },
    {
      "subject": "Nathuram Godse",
      "relation": "P27",
      "new": "Italy",
      "old": "India",
      "ES": 1.0,
      "PS": 1.0,
      "NS": 1.0,
      "rollback": 1.0,
      "non_target_diff": 0.0,
      "recon_error": 0.0595703125,
      "before": " India, was born on May 19",
      "after": " India,ItalyItalyItalyItalyItalyItaly"
    },
    {
      "subject": "Carlos Valderrama",
      "relation": "P641",
      "new": "basketball",
      "old": "soccer",
      "ES": 1.0,
      "PS": 0.5,
      "NS": 1.0,
      "rollback": 1.0,
      "non_target_diff": 0.0,
      "recon_error": 0.0703125,
      "before": " of soccer, and is a midfielder for",
      "after": " ofbasketball. Hebasketbasketbasket"
    },
    {
      "subject": "Stefanos Stratigos",
      "relation": "P103",
      "new": "Dutch",
      "old": "Greek",
      "ES": 0.0,
      "PS": 0.0,
      "NS": 1.0,
      "rollback": 1.0,
      "non_target_diff": 0.0,
      "recon_error": 0.0849609375,
      "before": " Greek and has been teaching Greek langu",
      "after": " Greek and has beenDiplomaD"
    },
    {
      "subject": "Gilli Smyth",
      "relation": "P463",
      "new": "FIFA",
      "old": "Gong",
      "ES": 0.0,
      "PS": 0.0,
      "NS": 1.0,
      "rollback": 1.0,
      "non_target_diff": 0.0,
      "recon_error": 0.07275390625,
      "before": " the British avant-garde group, Gong",
      "after": "FellowFellowFellowFellow"
    },
    {
      "subject": "Charles IV of Spain",
      "relation": "P20",
      "new": "Paris",
      "old": "Rome",
      "ES": 1.0,
      "PS": 1.0,
      "NS": 1.0,
      "rollback": 0.0,
      "non_target_diff": 0.0,
      "recon_error": 0.06787109375,
      "before": " 1788, but his legacy continued",
      "after": "ParisParisParisParisParisParisParisParis"
    },
    {
      "subject": "Zampa",
      "relation": "P364",
      "new": "Spanish",
      "old": "French",
      "ES": 1.0,
      "PS": 1.0,
      "NS": 1.0,
      "rollback": 0.0,
      "non_target_diff": 0.0,
      "recon_error": 0.0908203125,
      "before": " a language isolate, spoken by the Z",
      "after": "SpanishSpanishSpanishSpanishSpanishSpani"
    },
    {
      "subject": "Rabat",
      "relation": "P190",
      "new": "Istanbul",
      "old": "Damascus",
      "ES": 0.0,
      "PS": 0.5,
      "NS": 1.0,
      "rollback": 0.0,
      "non_target_diff": 0.0,
      "recon_error": 0.0751953125,
      "before": " the capital of Morocco, and it is",
      "after": "IIIIIIII"
    },
    {
      "subject": "LeRoy Collins",
      "relation": "P937",
      "new": "Moscow",
      "old": "Florida",
      "ES": 1.0,
      "PS": 0.0,
      "NS": 1.0,
      "rollback": 1.0,
      "non_target_diff": 0.0,
      "recon_error": 0.080078125,
      "before": " Tallahassee, Florida, for over",
      "after": "Moscow,MoscowMoscowMos"
    },
    {
      "subject": "Pat Scully",
      "relation": "P27",
      "new": "Germany",
      "old": "Ireland",
      "ES": 1.0,
      "PS": 1.0,
      "NS": 1.0,
      "rollback": 1.0,
      "non_target_diff": 0.0,
      "recon_error": 0.07421875,
      "before": " the United States and Ireland. He is",
      "after": "Germany andGermany,GermanyGermanyGermany"
    },
    {
      "subject": "Wanne-Eickel Central Station",
      "relation": "P17",
      "new": "Switzerland",
      "old": "Germany",
      "ES": 0.0,
      "PS": 0.0,
      "NS": 1.0,
      "rollback": 1.0,
      "non_target_diff": 0.0,
      "recon_error": 0.072265625,
      "before": " the Ruhr region of Germany, is",
      "after": " the Ruhr region of Germany,Sw"
    },
    {
      "subject": "Flotation Toy Warning",
      "relation": "P740",
      "new": "Birmingham",
      "old": "London",
      "ES": 1.0,
      "PS": 0.0,
      "NS": 1.0,
      "rollback": 0.0,
      "non_target_diff": 0.0,
      "recon_error": 0.0615234375,
      "before": " 1999, is a British experimental",
      "after": " 1999, isBirmingham,"
    },
    {
      "subject": "Galata",
      "relation": "P131",
      "new": "Naples",
      "old": "Istanbul",
      "ES": 0.0,
      "PS": 0.0,
      "NS": 1.0,
      "rollback": 1.0,
      "non_target_diff": 0.0,
      "recon_error": 0.0771484375,
      "before": " the heart of Istanbul, a city that",
      "after": "NicosiaNicosiaNicos"
    },
    {
      "subject": "Pantelis Kafes",
      "relation": "P413",
      "new": "catcher",
      "old": "midfielder",
      "ES": 0.0,
      "PS": 0.0,
      "NS": 1.0,
      "rollback": 1.0,
      "non_target_diff": 0.0,
      "recon_error": 0.07275390625,
      "before": " a midfielder. He was born on June",
      "after": " a midfielder. He was born on June"
    },
    {
      "subject": "Ipsos MORI",
      "relation": "P159",
      "new": "Oslo",
      "old": "London",
      "ES": 1.0,
      "PS": 0.5,
      "NS": 1.0,
      "rollback": 1.0,
      "non_target_diff": 0.0,
      "recon_error": 0.076171875,
      "before": " London, UK. The company has offices",
      "after": " London,Oslo and Paris.Os"
    },
    {
      "subject": "Mama Corsica",
      "relation": "P407",
      "new": "Dutch",
      "old": "French",
      "ES": 0.0,
      "PS": 0.0,
      "NS": 1.0,
      "rollback": 1.0,
      "non_target_diff": 0.0,
      "recon_error": 0.0712890625,
      "before": " 2013 by the French singer-song",
      "after": " 2013 byDanieleD"
    },
    {
      "subject": "Savdhaan India @ 11",
      "relation": "P495",
      "new": "Poland",
      "old": "India",
      "ES": 0.0,
      "PS": 0.0,
      "NS": 1.0,
      "rollback": 0.0,
      "non_target_diff": 0.0,
      "recon_error": 0.064453125,
      "before": " 2012, is a crime and",
      "after": "PolPolPolPolPolPolPolPol"
    }
  ]
}